tpux/__init__.py
tpux/cli.py
tpux/podrun.py
tpux/utils.py
tpux-0.1.6.dist-info/LICENSE
tpux-0.1.6.dist-info/METADATA
tpux-0.1.6.dist-info/WHEEL
tpux-0.1.6.dist-info/entry_points.txt
tpux-0.1.6.dist-info/top_level.txt
tpux-0.1.6.dist-info/RECORD
